{"@context":"http://iiif.io/api/presentation/3/context.json","id":"https://zooniverse.github.io/iiif-annotations/annotations/titles/16.json","type":"AnnotationPage","partOf":{"id":"https://zooniverse.github.io/iiif-annotations/annotations/titles.json","type":"AnnotationCollection"},"items":[{"type":"Annotation","motivation":"tagging","body":{"type":"TextualBody","value":"ROB ROY; OR THE TRAVELLER'S PORTMANTEAU","language":"en","format":"text/plain"},"target":{"type":"SpecificResource","source":{"id":"https://api.bl.uk/metadata/iiif/ark:/81055/vdc_100022589176.0x0001d3","type":"Canvas","partOf":{"id":"https://api.bl.uk/metadata/iiif/ark:/81055/vdc_100022589176.0x000002/manifest.json","type":"Manifest"}},"selector":{"type":"FragmentSelector","conformsTo":"http://www.w3.org/TR/media-frags/","value":"xywh=470,543,1616,276"}},"id":"https://zooniverse.github.io/iiif-annotations/bldigital/in-the-spotlight/titles/158"},{"type":"Annotation","motivation":"tagging","body":{"type":"TextualBody","value":"GIOVANNI IN LONDON","language":"en","format":"text/plain"},"target":{"type":"SpecificResource","source":{"id":"https://api.bl.uk/metadata/iiif/ark:/81055/vdc_100022589176.0x0001d3","type":"Canvas","partOf":{"id":"https://api.bl.uk/metadata/iiif/ark:/81055/vdc_100022589176.0x000002/manifest.json","type":"Manifest"}},"selector":{"type":"FragmentSelector","conformsTo":"http://www.w3.org/TR/media-frags/","value":"xywh=497,1267,1559,106"}},"id":"https://zooniverse.github.io/iiif-annotations/bldigital/in-the-spotlight/titles/159"},{"type":"Annotation","motivation":"tagging","body":{"type":"TextualBody","value":"THE FORTUNATE YOUTH","language":"en","format":"text/plain"},"target":{"type":"SpecificResource","source":{"id":"https://api.bl.uk/metadata/iiif/ark:/81055/vdc_100022589176.0x0001d3","type":"Canvas","partOf":{"id":"https://api.bl.uk/metadata/iiif/ark:/81055/vdc_100022589176.0x000002/manifest.json","type":"Manifest"}},"selector":{"type":"FragmentSelector","conformsTo":"http://www.w3.org/TR/media-frags/","value":"xywh=250,1711,2032,210"}},"id":"https://zooniverse.github.io/iiif-annotations/bldigital/in-the-spotlight/titles/160"},{"type":"Annotation","motivation":"tagging","body":{"type":"TextualBody","value":"GIOVANNI IN LONDON","language":"en","format":"text/plain"},"target":{"type":"SpecificResource","source":{"id":"https://api.bl.uk/metadata/iiif/ark:/81055/vdc_100022589176.0x0001d3","type":"Canvas","partOf":{"id":"https://api.bl.uk/metadata/iiif/ark:/81055/vdc_100022589176.0x000002/manifest.json","type":"Manifest"}},"selector":{"type":"FragmentSelector","conformsTo":"http://www.w3.org/TR/media-frags/","value":"xywh=281,2219,1973,173"}},"id":"https://zooniverse.github.io/iiif-annotations/bldigital/in-the-spotlight/titles/161"},{"type":"Annotation","motivation":"tagging","body":{"type":"TextualBody","value":"Rob Roy; or the traveller's portmanteau","language":"en","format":"text/plain"},"target":{"type":"SpecificResource","source":{"id":"https://api.bl.uk/metadata/iiif/ark:/81055/vdc_100022589176.0x0001d3","type":"Canvas","partOf":{"id":"https://api.bl.uk/metadata/iiif/ark:/81055/vdc_100022589176.0x000002/manifest.json","type":"Manifest"}},"selector":{"type":"FragmentSelector","conformsTo":"http://www.w3.org/TR/media-frags/","value":"xywh=287,571,1834,245"}},"id":"https://zooniverse.github.io/iiif-annotations/bldigital/in-the-spotlight/titles/260"},{"type":"Annotation","motivation":"tagging","body":{"type":"TextualBody","value":"Giovanni in London","language":"en","format":"text/plain"},"target":{"type":"SpecificResource","source":{"id":"https://api.bl.uk/metadata/iiif/ark:/81055/vdc_100022589176.0x0001d3","type":"Canvas","partOf":{"id":"https://api.bl.uk/metadata/iiif/ark:/81055/vdc_100022589176.0x000002/manifest.json","type":"Manifest"}},"selector":{"type":"FragmentSelector","conformsTo":"http://www.w3.org/TR/media-frags/","value":"xywh=449,1269,1628,100"}},"id":"https://zooniverse.github.io/iiif-annotations/bldigital/in-the-spotlight/titles/261"},{"type":"Annotation","motivation":"tagging","body":{"type":"TextualBody","value":"The fortunate youth","language":"en","format":"text/plain"},"target":{"type":"SpecificResource","source":{"id":"https://api.bl.uk/metadata/iiif/ark:/81055/vdc_100022589176.0x0001d3","type":"Canvas","partOf":{"id":"https://api.bl.uk/metadata/iiif/ark:/81055/vdc_100022589176.0x000002/manifest.json","type":"Manifest"}},"selector":{"type":"FragmentSelector","conformsTo":"http://www.w3.org/TR/media-frags/","value":"xywh=222,1745,2054,140"}},"id":"https://zooniverse.github.io/iiif-annotations/bldigital/in-the-spotlight/titles/262"},{"type":"Annotation","motivation":"tagging","body":{"type":"TextualBody","value":"Giovanni in London","language":"en","format":"text/plain"},"target":{"type":"SpecificResource","source":{"id":"https://api.bl.uk/metadata/iiif/ark:/81055/vdc_100022589176.0x0001d3","type":"Canvas","partOf":{"id":"https://api.bl.uk/metadata/iiif/ark:/81055/vdc_100022589176.0x000002/manifest.json","type":"Manifest"}},"selector":{"type":"FragmentSelector","conformsTo":"http://www.w3.org/TR/media-frags/","value":"xywh=230,2233,2045,144"}},"id":"https://zooniverse.github.io/iiif-annotations/bldigital/in-the-spotlight/titles/263"}],"previous":{"id":"https://zooniverse.github.io/iiif-annotations/annotations/titles/15.json","type":"AnnotationPage"},"next":{"id":"https://zooniverse.github.io/iiif-annotations/annotations/titles/17.json","type":"AnnotationPage"}}